assets/__init__.py
mj_envs/__init__.py
mj_envs/asset_manager.py
mj_envs/dirs.py
mj_envs/make.py
mj_envs/assets/__init__.py
mj_envs/cfgs/__init__.py
mj_envs/cfgs/bimanual_insertion.py
mj_envs/cfgs/bolt_nut_sort.py
mj_envs/cfgs/cvs_travel_sort.py
mj_envs/cfgs/flip_box.py
mj_envs/cfgs/handover.py
mj_envs/cfgs/hang_things_on_wall.py
mj_envs/cfgs/jenga.py
mj_envs/cfgs/lego.py
mj_envs/cfgs/magna.py
mj_envs/cfgs/new_mug_hang.py
mj_envs/cfgs/pick_acv.py
mj_envs/cfgs/pick_jasminetea.py
mj_envs/cfgs/pick_mug.py
mj_envs/cfgs/pick_teastea.py
mj_envs/cfgs/pyramid.py
mj_envs/cfgs/table_bookshelf.py
mj_envs/cfgs/test.py
mj_envs/cfgs/toy_five_insertions.py
mj_envs/envs/__init__.py
mj_envs/envs/base_env.py
mj_envs/mink/__init__.py
mj_envs/mink/configuration.py
mj_envs/mink/constants.py
mj_envs/mink/exceptions.py
mj_envs/mink/py.typed
mj_envs/mink/solve_ik.py
mj_envs/mink/utils.py
mj_envs/mink/lie/__init__.py
mj_envs/mink/lie/base.py
mj_envs/mink/lie/se3.py
mj_envs/mink/lie/so3.py
mj_envs/mink/lie/utils.py
mj_envs/mink/limits/__init__.py
mj_envs/mink/limits/collision_avoidance_limit.py
mj_envs/mink/limits/configuration_limit.py
mj_envs/mink/limits/exceptions.py
mj_envs/mink/limits/limit.py
mj_envs/mink/limits/velocity_limit.py
mj_envs/mink/tasks/__init__.py
mj_envs/mink/tasks/com_task.py
mj_envs/mink/tasks/damping_task.py
mj_envs/mink/tasks/exceptions.py
mj_envs/mink/tasks/frame_task.py
mj_envs/mink/tasks/posture_task.py
mj_envs/mink/tasks/relative_com_task.py
mj_envs/mink/tasks/relative_frame_task.py
mj_envs/mink/tasks/task.py
mj_envs/robot_cfgs/__init__.py
mj_envs/robot_cfgs/aloha.py
mj_envs/robot_cfgs/dual_panda.py
mj_envs/robot_cfgs/dual_ur5e.py
mj_envs/robot_cfgs/eyesight.py
mj_envs/robot_cfgs/freefloating_dual_allegro.py
mj_envs/robot_cfgs/left_panda.py
mj_envs/robot_cfgs/rby1.py
mj_envs/robot_cfgs/rby1_mobile.py
mj_envs/robot_cfgs/right_panda.py
mj_envs/robot_cfgs/unitree_g1.py
mj_envs/utils/__init__.py
mj_envs/utils/lie.py
mj_envs/utils/mesh_download.py
mj_envs/utils/misc.py
mj_envs-0.5.5.dist-info/METADATA
mj_envs-0.5.5.dist-info/WHEEL
mj_envs-0.5.5.dist-info/top_level.txt
mj_envs-0.5.5.dist-info/RECORD
